wordconstraints/__init__.py
wordconstraints/wordconstraints.py
wordconstraints-0.0.2.dist-info/LICENSE
wordconstraints-0.0.2.dist-info/METADATA
wordconstraints-0.0.2.dist-info/WHEEL
wordconstraints-0.0.2.dist-info/top_level.txt
wordconstraints-0.0.2.dist-info/RECORD
