Metadata-Version: 2.1
Name: wordconstraints
Version: 0.0.2
Summary: For filtering words by letters and type.
Home-page: https://github.com/MeganKW/wordconstraints
Author: Megan Kinniment
Author-email: megan.kinniment@gmail.com
Classifier: Programming Language :: Python :: 3
Classifier: License :: OSI Approved :: MIT License
Classifier: Operating System :: OS Independent
Requires-Python: >=3.10
License-File: LICENSE
